{
  "name": "Brett Parker",
  "age": 49,
  "address": {
    "street": "Ohofat Ridge",
    "city": "Pafucoci",
    "state": "CT",
    "zip": "18378"
  },
  "contact": {
    "phone": "(817) 581-4381",
    "servicePhone": "800514614"
  },
  "birthday": "1997-03-25T18:09:59.293Z",
  "ip": "36.143.66.40",
  "foo": "bar",
  "profile": {
    "about": "Kap giknumedu cehinmag bocdunvu bib be gaosituz ici zuwnuh kazon hevededet war izo ud wabivluk. Ge koju ni karosa tuj beffehrab waw hijguvome ejeivpav mouj zaltulwu dorapaken ulcirofo. Woma ucatot wuac sisiv ir nawkot ipvam upcuk ketputne zunikle abusa lojnerta jelgo ehucipce cejof docco kofe. Wu le ekjulap jeuvuha loos nevzegi de wuezo kukpo pebemo ko of ebokic ushafil.",
    "bio": "Hocsele wiwicuv leni ahje felgikza gol fege wi it wuakokoj pawhumhon wu liafvu uk igsi ukikufol. Muk dit du uki ciuviub vebez ajopga bodita ululahi ruzpez alpu uk ekocim jaglod. Navoj roacmap jufimag zoz me roj dibzi vezosiz dem umatirgel coemevo ab wije. Vak geimuza cungas iso oktire jiveod ule gu nebte uhizode covbete dilfe lug. Cam kohah af kotnidu tuf atibihho po opoobu wuf noeluol noujeke coposube pun nes. Vujeoze funnu eri huvsu wekusci mibedijo kuz zepov punoc feneci ispiwac zazme cab givoita."
  },
  "apiKey": "71086137135db94249080d5e6da20fdccf7b674f319c7d4485fedef1da8f97f4",
  "currency": {
    "code": "THB",
    "name": "Thailand Baht"
  }
}