{
  "name": "Dale Riley",
  "age": 26,
  "address": {
    "street": "Eleji Court",
    "city": "Fojikij",
    "state": "NH",
    "zip": "09842"
  },
  "contact": {
    "phone": "(802) 620-3929",
    "servicePhone": "800735623"
  },
  "birthday": "1961-01-01T07:38:31.868Z",
  "ip": "28.148.168.6",
  "foo": "bar",
  "profile": {
    "about": "Na bonaj jak leufu uk jocehe as devuwo fenenoj uwimulot ba ekzuesa tewoc heguvgic egifeg ge jeknavne. Lifocno felu be ed feiptah adi julvo wuku lircukso iti kapaf zetlam asonevu ceboho ket okgaf. Suse wopu uve haftolka zu wof ko ocevas zola ilsil ikaufe zopmez vijuf ezizit zak. Murpoki ka fahre lucfer opo ugahage ovcinuk asewaka vociha mum acemuluv vokogak. Ratoj posrubat uka budziboc ti uha kena so cabe ijiwiv zemhu fo po ewudihiw gunlov mifwes pef la. Gul otefic rupalin wu cataor totactah ziteso hac poug losibgoc gu zogod tiekkam fo.",
    "bio": "Igivuc asu sucasmu wuiv gi uhni gin gut kajo ardeg mefara zu ewuba. Geppiw zarar uckon onu tojtemwen lociluha cubege uhuguija eridof povuj mobjaj podfamej sos tagogweg esse fa im gi. Romekpeg rog reafkuc kog izjahner fo nu ga ok ballabdu tacfezte ewten ito jeencom viweig pibur. Udaalati veepvur ef povlu lasigfic lu zop izupel bu ut ota ve. Palweem epafu ledlen dibere lu ja huv diiti roso siju sedisemu bo. Vawa gudmolhe osahel ip hatrodhoc hah vof minag nievi esizim poh moipuiz mipalo izoepi ob. Itresego vo tofepup fu fol guttamto bij kicahgej jadod habom ne fepuwvul ov ipjo turpa zot tohisuv teah."
  },
  "apiKey": "777de8e15f55981306e9ac769d68143e820b91d2bf3cbcb9615af4665f924f07",
  "currency": {
    "code": "EUR",
    "name": "Euro Member Countries"
  }
}